voyage_agents/__init__.py
voyage_agents/agents/__init__.py
voyage_agents/agents/agent.py
voyage_agents/agents/question_answerer.py
voyage_agents/agents/reflector.py
voyage_agents/agents/tool_caller.py
voyage_agents/core/__init__.py
voyage_agents/core/grammar.py
voyage_agents/core/manager.py
voyage_agents/core/message.py
voyage_agents/prompt/__init__.py
voyage_agents/prompt/prompt.py
voyage_agents/tool/__init__.py
voyage_agents/tool/tool.py
voyage_agents-0.0.6.dist-info/LICENSE
voyage_agents-0.0.6.dist-info/METADATA
voyage_agents-0.0.6.dist-info/WHEEL
voyage_agents-0.0.6.dist-info/top_level.txt
voyage_agents-0.0.6.dist-info/RECORD
