Metadata-Version: 2.1
Name: voyage-agents
Version: 0.0.6
Summary: AI agent and tool calling library for small local models using llama.cpp.
Author: Ville Kuosmanen
Project-URL: Homepage, https://github.com/villekuosmanen/voyage-agents
Project-URL: Issues, https://github.com/villekuosmanen/voyage-agents/issues
Classifier: Programming Language :: Python :: 3
Classifier: License :: OSI Approved :: MIT License
Classifier: Operating System :: OS Independent
Requires-Python: >=3.8
License-File: LICENSE
